cli.py
cosign.py
gitutil.py
gziputil.py
http_requests.py
ioutil.py
reutil.py
signingserver.py
tarutil.py
version.py
ci/VERSION
ci/__init__.py
ci/log.py
ci/paths.py
ci/util.py
cnudie/__init__.py
cnudie/access.py
cnudie/purge.py
cnudie/retrieve.py
cnudie/retrieve_async.py
cnudie/util.py
concourse/client/__init__.py
concourse/client/api.py
concourse/client/model.py
concourse/client/routes.py
concourse/client/util.py
concourse/model/__init__.py
concourse/model/base.py
concourse/model/job.py
concourse/model/pipeline.py
concourse/model/resources.py
concourse/model/step.py
concourse/model/traits/__init__.py
concourse/model/traits/component_descriptor.py
concourse/model/traits/cronjob.py
concourse/model/traits/draft_release.py
concourse/model/traits/images.py
concourse/model/traits/meta.py
concourse/model/traits/notifications.py
concourse/model/traits/options.py
concourse/model/traits/publish.py
concourse/model/traits/pullrequest.py
concourse/model/traits/release.py
concourse/model/traits/scheduling.py
concourse/model/traits/slack.py
concourse/model/traits/update_component_deps.py
concourse/model/traits/version.py
concourse/steps/__init__.py
concourse/steps/build_oci_image.py
concourse/steps/cfg_reporting.py
concourse/steps/component_descriptor.py
concourse/steps/component_descriptor_util.py
concourse/steps/meta.py
concourse/steps/notification.py
concourse/steps/release.py
concourse/steps/replicate_pipelines.py
concourse/steps/replicate_secrets.py
concourse/steps/update_component_deps.py
concourse/steps/version.py
concourse/templates/__init__.py
ctt/__init__.py
ctt/__main__.py
ctt/filters.py
ctt/model.py
ctt/oci_platform.py
ctt/oci_util.py
ctt/process_dependencies.py
ctt/processors.py
ctt/replicate.py
ctt/targets.py
ctt/uploaders.py
ctt/util.py
ctt/test/__init__.py
ctt/test/filters_test.py
ctt/test/platform_test.py
ctt/test/process_deps_test.py
ctt/test/processors_test.py
delivery/__init__.py
delivery/client.py
delivery/jwt.py
delivery/model.py
github/__init__.py
gardener_gha_libs-1.2740.0.dist-info/LICENSE
gardener_gha_libs-1.2740.0.dist-info/METADATA
gardener_gha_libs-1.2740.0.dist-info/WHEEL
gardener_gha_libs-1.2740.0.dist-info/top_level.txt
gardener_gha_libs-1.2740.0.dist-info/RECORD
