Metadata-Version: 2.1
Name: gardener-gha-libs
Version: 1.2740.0
Summary: Gardener CI/CD Libraries for GitHubActions
Requires-Python: >=3.12
License-File: LICENSE
Requires-Dist: GitPython
Requires-Dist: awesomeversion
Requires-Dist: cachecontrol <1
Requires-Dist: cachetools
Requires-Dist: cryptography
Requires-Dist: dacite
Requires-Dist: deepmerge
Requires-Dist: deprecated
Requires-Dist: ensure
Requires-Dist: flake8
Requires-Dist: gardener-oci
Requires-Dist: gardener-ocm
Requires-Dist: github3.py <5.0.0
Requires-Dist: html2text
Requires-Dist: jq
Requires-Dist: jsonpath-ng
Requires-Dist: jsonschema
Requires-Dist: pycryptodome
Requires-Dist: pyjwt
Requires-Dist: pytest
Requires-Dist: python-dateutil
Requires-Dist: python-magic
Requires-Dist: pyyaml
Requires-Dist: requests
Requires-Dist: ruamel.yaml ==0.17.21
Requires-Dist: semver
Requires-Dist: tabulate
Requires-Dist: termcolor
Requires-Dist: yamllint
